{
  "type": "FeatureCollection",
  "features": [
    {
      "type": "Feature",
      "properties": {},
      "geometry": {
        "type": "Polygon",
        "coordinates": [
          [
            [
              12.565265057102135,
              55.70118781649569
            ],
            [
              12.565264497424911,
              55.70118407928158
            ],
            [
              12.565264786040972,
              55.70117872736189
            ],
            [
              12.565266319138221,
              55.701173434060664
            ],
            [
              12.565269103261276,
              55.70116831608059
            ],
            [
              12.565273078850343,
              55.70116344637611
            ],
            [
              12.565275706940193,
              55.70116093716933
            ],
            [
              12.565280272498715,
              55.70115779123978
            ],
            [
              12.565285741077904,
              55.70115514137017
            ],
            [
              12.565291958744758,
              55.701153080175104
            ],
            [
              12.56530265347731,
              55.70115111863127
            ],
            [
              12.565315340052862,
              55.70114948989471
            ],
            [
              12.565328241770844,
              55.70114857620083
            ],
            [
              12.565338510516241,
              55.70114894968495
            ],
            [
              12.565369853142908,
              55.701150554776895
            ],
            [
              12.565377723992103,
              55.70115101607567
            ],
            [
              12.56539502753109,
              55.701152548753946
            ],
            [
              12.565412068305806,
              55.70115478704912
            ],
            [
              12.565428797619772,
              55.70115771385985
            ],
            [
              12.565445087796048,
              55.70116132248395
            ],
            [
              12.565446635035297,
              55.70116167222831
            ],
            [
              12.565459811602157,
              55.70116424023027
            ],
            [
              12.565473346819585,
              55.701166109882536
            ],
            [
              12.565483352590634,
              55.701166901421125
            ],
            [
              12.565494518395838,
              55.70116709709659
            ],
            [
              12.565505643919046,
              55.70116657459963
            ],
            [
              12.56551252586126,
              55.70116529229273
            ],
            [
              12.565531646887914,
              55.70116121204504
            ],
            [
              12.56553844409277,
              55.701159553834145
            ],
            [
              12.56555000105294,
              55.70115736117863
            ],
            [
              12.565561899326777,
              55.70115586333657
            ],
            [
              12.565567494562226,
              55.701155188141435
            ],
            [
              12.565575780095482,
              55.70115481528444
            ],
            [
              12.565584073615025,
              55.70115515218983
            ],
            [
              12.565592184359835,
              55.701156202269686
            ],
            [
              12.565597624445076,
              55.70115730011973
            ],
            [
              12.565611994433324,
              55.70116071841496
            ],
            [
              12.565625812498766,
              55.70116479358373
            ],
            [
              12.56563899664024,
              55.70116948216234
            ],
            [
              12.565643313812677,
              55.701170986500955
            ],
            [
              12.565657562184272,
              55.701176491753
            ],
            [
              12.565671063845036,
              55.70118258547399
            ],
            [
              12.565683736289802,
              55.70118921522319
            ],
            [
              12.565691893601395,
              55.70119336468515
            ],
            [
              12.565705139997785,
              55.701200864807966
            ],
            [
              12.565716177532853,
              55.701208134857424
            ],
            [
              12.565727935545489,
              55.701216901691055
            ],
            [
              12.565731579316774,
              55.7012200176072
            ],
            [
              12.565736122170305,
              55.70122497757308
            ],
            [
              12.56573948736776,
              55.70123021920347
            ],
            [
              12.565741639086513,
              55.70123567125005
            ],
            [
              12.565746314313097,
              55.70128355568309
            ],
            [
              12.565746817200766,
              55.70128571234921
            ],
            [
              12.565748898571846,
              55.701290761277356
            ],
            [
              12.565752193424927,
              55.70129559978908
            ],
            [
              12.565756633137196,
              55.701300139250385
            ],
            [
              12.56577632332349,
              55.7013141468887
            ],
            [
              12.56578630105282,
              55.70131982737018
            ],
            [
              12.565792005251446,
              55.70132393084734
            ],
            [
              12.565798680972303,
              55.701329751271864
            ],
            [
              12.565804263555428,
              55.70133594171076
            ],
            [
              12.565805636107696,
              55.701339134198896
            ],
            [
              12.565806108011724,
              55.70134300777361
            ],
            [
              12.565805305648993,
              55.70134685921277
            ],
            [
              12.56580326965931,
              55.70135056198319
            ],
            [
              12.565800057083132,
              55.70135399824442
            ],
            [
              12.56579577164423,
              55.70135703134873
            ],
            [
              12.565739023252007,
              55.701384205173085
            ],
            [
              12.565738761566019,
              55.70138436261868
            ],
            [
              12.56573291837466,
              55.70138827727033
            ],
            [
              12.565728101864645,
              55.701392622863686
            ],
            [
              12.565724402381594,
              55.701397307921276
            ],
            [
              12.565723686570307,
              55.7014052554954
            ],
            [
              12.565724234670217,
              55.70141332423894
            ],
            [
              12.565726036610503,
              55.70142133460897
            ],
            [
              12.565738565200748,
              55.70144780834391
            ],
            [
              12.565753435419078,
              55.70147659456097
            ],
            [
              12.565768792722002,
              55.70150697159778
            ],
            [
              12.565769008161114,
              55.70150740806525
            ],
            [
              12.565770396478515,
              55.70151173252651
            ],
            [
              12.565770531456733,
              55.701516124338845
            ],
            [
              12.56576939065168,
              55.701520467083775
            ],
            [
              12.565766999813777,
              55.70152465246692
            ],
            [
              12.56576344777748,
              55.701528562079034
            ],
            [
              12.565758824384691,
              55.70153209546531
            ],
            [
              12.565753921460615,
              55.701535184544305
            ],
            [
              12.565747411434172,
              55.70153827541292
            ],
            [
              12.56574018409795,
              55.70154077704059
            ],
            [
              12.565732348716484,
              55.70154265152808
            ],
            [
              12.565724124825687,
              55.70154384103133
            ],
            [
              12.565715670388258,
              55.70154432475221
            ],
            [
              12.565707191561287,
              55.70154409001692
            ],
            [
              12.565654108759395,
              55.701537895559525
            ],
            [
              12.565599226305347,
              55.701529971984854
            ],
            [
              12.56559472984323,
              55.70152924365998
            ],
            [
              12.565585529322478,
              55.70152720662333
            ],
            [
              12.565576881237384,
              55.701524521688114
            ],
            [
              12.565572430664089,
              55.70152205821492
            ],
            [
              12.56556823782107,
              55.70151879935058
            ],
            [
              12.565565138629218,
              55.701515179450574
            ],
            [
              12.565562188472557,
              55.7015082589683
            ],
            [
              12.565560341167272,
              55.701498020843
            ],
            [
              12.565560004884727,
              55.701497415799984
            ],
            [
              12.565555684503204,
              55.70149103203684
            ],
            [
              12.565550219257805,
              55.70148494732207
            ],
            [
              12.565543644467576,
              55.701479223926704
            ],
            [
              12.565524447295179,
              55.70146152311227
            ],
            [
              12.565523676258064,
              55.7014608269977
            ],
            [
              12.565518819781143,
              55.701455665952295
            ],
            [
              12.56551510817013,
              55.701450205858634
            ],
            [
              12.565512625944411,
              55.7014445350664
            ],
            [
              12.565511393028675,
              55.701438725108616
            ],
            [
              12.565511415464737,
              55.70143288371089
            ],
            [
              12.56551271317722,
              55.70142708240615
            ],
            [
              12.565512927244983,
              55.701426359685314
            ],
            [
              12.565515914269678,
              55.70141890167196
            ],
            [
              12.565520121541649,
              55.70141163750009
            ],
            [
              12.565525520791246,
              55.70140463057836
            ],
            [
              12.56554217731509,
              55.701387249981835
            ],
            [
              12.5655527425345,
              55.70137815573168
            ],
            [
              12.565564379375681,
              55.70136518725487
            ],
            [
              12.565569657045558,
              55.70135771522592
            ],
            [
              12.56557198977044,
              55.701352209922334
            ],
            [
              12.565573302144605,
              55.70134610282536
            ],
            [
              12.565573371038452,
              55.70133995506743
            ],
            [
              12.565572153293926,
              55.701333848295754
            ],
            [
              12.565570742496751,
              55.70133195948087
            ],
            [
              12.565565671097522,
              55.701326370946575
            ],
            [
              12.565559506054655,
              55.701321143447494
            ],
            [
              12.565552314984105,
              55.701316347663294
            ],
            [
              12.565544212688751,
              55.70131204444338
            ],
            [
              12.565542999060174,
              55.70131140117622
            ],
            [
              12.565534534376845,
              55.701307445911205
            ],
            [
              12.56552532297593,
              55.701304079115474
            ],
            [
              12.565515477645642,
              55.701301325729695
            ],
            [
              12.565513382858118,
              55.70130085997378
            ],
            [
              12.565501179689878,
              55.7012986250261
            ],
            [
              12.565488649163523,
              55.70129707887969
            ],
            [
              12.565481610530018,
              55.70129613542273
            ],
            [
              12.565455304852428,
              55.70129213082665
            ],
            [
              12.565429342437561,
              55.70128743713831
            ],
            [
              12.565403803777832,
              55.70128207089056
            ],
            [
              12.565393084423812,
              55.70127905455697
            ],
            [
              12.565379657002167,
              55.70127456799837
            ],
            [
              12.56536691171034,
              55.70126947615249
            ],
            [
              12.565354945943636,
              55.70126381322212
            ],
            [
              12.565346811887123,
              55.70125951055774
            ],
            [
              12.565331222093334,
              55.701250515677415
            ],
            [
              12.565316559934855,
              55.701241036924834
            ],
            [
              12.565302874612469,
              55.70123110037882
            ],
            [
              12.56529890862104,
              55.70122819689469
            ],
            [
              12.5652898840111,
              55.701220782974566
            ],
            [
              12.565281952042367,
              55.70121299006645
            ],
            [
              12.56527513112855,
              55.70120486277196
            ],
            [
              12.565269487877211,
              55.70119645381692
            ],
            [
              12.565265057102135,
              55.70118781649569
            ]
          ]
        ]
      }
    },
    {
      "type": "Feature",
      "properties": {},
      "geometry": {
        "type": "Polygon",
        "coordinates": [
          [
            [
              -49.21875,
              17.97873309555617
            ],
            [
              25.3125,
              -47.98992166741417
            ],
            [
              111.09374999999999,
              15.284185114076445
            ],
            [
              85.78125,
              71.96538769913127
            ],
            [
              -49.21875,
              17.97873309555617
            ]
          ]
        ]
      }
    }
  ]
}